openai_usage/VERSION
openai_usage/__init__.py
openai_usage/extra/__init__.py
openai_usage/extra/open_router.py
openai_usage/models.json
openai_usage/pricing.py
openai_usage-0.7.3.dist-info/METADATA
openai_usage-0.7.3.dist-info/WHEEL
openai_usage-0.7.3.dist-info/licenses/LICENSE
openai_usage-0.7.3.dist-info/RECORD
