Metadata-Version: 2.4
Name: openai-usage
Version: 0.7.3
Summary: Simple Library for OpenAI Usage
License: MIT
License-File: LICENSE
Author: Allen Chou
Author-email: f1470891079@gmail.com
Requires-Python: >=3.11,<4
Classifier: License :: OSI Approved :: MIT License
Classifier: Programming Language :: Python :: 3
Classifier: Programming Language :: Python :: 3.11
Classifier: Programming Language :: Python :: 3.12
Classifier: Programming Language :: Python :: 3.13
Classifier: Programming Language :: Python :: 3.14
Requires-Dist: dictpress
Requires-Dist: openai
Requires-Dist: openai-agents
Requires-Dist: pydantic
Requires-Dist: str-or-none
Project-URL: Homepage, https://github.com/allen2c/openai-usage
Project-URL: PyPI, https://pypi.org/project/openai-usage/
Project-URL: Repository, https://github.com/allen2c/openai-usage
